__init__.py
stdio.py
PyStdio-1.0.1.dist-info/LICENSE
PyStdio-1.0.1.dist-info/METADATA
PyStdio-1.0.1.dist-info/WHEEL
PyStdio-1.0.1.dist-info/top_level.txt
PyStdio-1.0.1.dist-info/RECORD
