Metadata-Version: 2.1
Name: PyStdio
Version: 1.0.1
Summary: The definitive standard IO library for python.
Author: Choro08, Iland69
Project-URL: Homepage, https://github.com/Choro08/PyStdio
Project-URL: Issues, https://github.com/Choro08/PyStdio/issues
Classifier: Programming Language :: Python :: 3
Classifier: License :: OSI Approved :: MIT License
Classifier: Operating System :: OS Independent
Requires-Python: >=3.11
License-File: LICENSE
